tokenlens/__init__.py
tokenlens/cli.py
tokenlens/tokenizer.py
tokenlens/providers/__init__.py
tokenlens/providers/adobe_provider.py
tokenlens/providers/ai21_provider.py
tokenlens/providers/amazon_provider.py
tokenlens/providers/anthropic_provider.py
tokenlens/providers/art_providers.py
tokenlens/providers/avatar_providers.py
tokenlens/providers/cohere_provider.py
tokenlens/providers/deepmind_provider.py
tokenlens/providers/factory.py
tokenlens/providers/gaming_providers.py
tokenlens/providers/google_provider.py
tokenlens/providers/haygen_provider.py
tokenlens/providers/huggingface_provider.py
tokenlens/providers/meta_provider.py
tokenlens/providers/microsoft_provider.py
tokenlens/providers/midjourney_provider.py
tokenlens/providers/mistral_provider.py
tokenlens/providers/openai_provider.py
tokenlens/providers/provider_factory.py
tokenlens/providers/provider_template.py
tokenlens/providers/qwen_provider.py
tokenlens/providers/stability_provider.py
tokenlens/providers/stanford_provider.py
tokenlens/providers/voice_providers.py
tokenlens/tokenizers/__init__.py
tokenlens/tokenizers/ai21_tokenizer.py
tokenlens/tokenizers/anthropic_tokenizer.py
tokenlens/tokenizers/base.py
tokenlens/tokenizers/cohere_tokenizer.py
tokenlens/tokenizers/deepmind_tokenizer.py
tokenlens/tokenizers/factory.py
tokenlens/tokenizers/google_tokenizer.py
tokenlens/tokenizers/huggingface_tokenizer.py
tokenlens/tokenizers/meta_tokenizer.py
tokenlens/tokenizers/mistral_tokenizer.py
tokenlens/tokenizers/openai_tokenizer.py
tokenlens/tokenizers/qwen_tokenizer.py
tokenlens/tokenizers/stanford_tokenizer.py
tokenlens-0.1.6.dist-info/LICENSE
tokenlens-0.1.6.dist-info/METADATA
tokenlens-0.1.6.dist-info/WHEEL
tokenlens-0.1.6.dist-info/top_level.txt
tokenlens-0.1.6.dist-info/RECORD
