Metadata-Version: 2.1
Name: tokenlens
Version: 0.1.6
Summary: A library for accurate token counting and limit validation across various LLM providers
Home-page: https://github.com/tokenlens/tokenlens
Author: TokenLens Team
Author-email: Giri Ramanathan <vgiri2015@gmail.com>
License: MIT
Project-URL: Homepage, https://github.com/vgiri2015/tokenlens
Project-URL: Documentation, https://github.com/vgiri2015/tokenlens/tree/main/docs
Project-URL: Repository, https://github.com/vgiri2015/tokenlens.git
Project-URL: Bug Tracker, https://github.com/vgiri2015/tokenlens/issues
Keywords: llm,tokens,openai,mistral,anthropic,tokenizer
Classifier: Development Status :: 4 - Beta
Classifier: Intended Audience :: Developers
Classifier: License :: OSI Approved :: MIT License
Classifier: Programming Language :: Python :: 3
Classifier: Programming Language :: Python :: 3.8
Classifier: Programming Language :: Python :: 3.9
Classifier: Programming Language :: Python :: 3.10
Classifier: Programming Language :: Python :: 3.11
Classifier: Topic :: Scientific/Engineering :: Artificial Intelligence
Classifier: Topic :: Software Development :: Libraries :: Python Modules
Requires-Python: >=3.8
License-File: LICENSE
Requires-Dist: tiktoken>=0.5.2
Requires-Dist: pydantic>=1.10.13
Requires-Dist: python-dotenv>=1.0.0
Requires-Dist: PyYAML>=6.0.1
Provides-Extra: openai
Requires-Dist: openai>=1.3.7; extra == "openai"
Provides-Extra: anthropic
Requires-Dist: anthropic>=0.3.0; extra == "anthropic"
Provides-Extra: google
Requires-Dist: google-generativeai>=0.3.0; extra == "google"
Provides-Extra: huggingface
Requires-Dist: transformers>=4.30.0; extra == "huggingface"
Requires-Dist: huggingface-hub>=0.16.0; extra == "huggingface"
Provides-Extra: mistral
Requires-Dist: mistralai>=0.0.7; extra == "mistral"
Provides-Extra: stability
Requires-Dist: stability-sdk>=0.8.0; extra == "stability"
Provides-Extra: media
Requires-Dist: torch>=2.0.0; extra == "media"
Requires-Dist: Pillow>=9.0.0; extra == "media"
Requires-Dist: numpy>=1.21.0; extra == "media"
Provides-Extra: all
Requires-Dist: openai>=1.3.7; extra == "all"
Requires-Dist: anthropic>=0.3.0; extra == "all"
Requires-Dist: google-generativeai>=0.3.0; extra == "all"
Requires-Dist: transformers>=4.30.0; extra == "all"
Requires-Dist: huggingface-hub>=0.16.0; extra == "all"
Requires-Dist: mistralai>=0.0.7; extra == "all"
Requires-Dist: stability-sdk>=0.8.0; extra == "all"
Requires-Dist: torch>=2.0.0; extra == "all"
Requires-Dist: Pillow>=9.0.0; extra == "all"
Requires-Dist: numpy>=1.21.0; extra == "all"
